dorkas_core-0.1.3.dist-info/METADATA
dorkas_core-0.1.3.dist-info/WHEEL
dorkas_core/__init__.py
dorkas_core/dorkas_core.cpython-311-darwin.so
dorkas_core-0.1.3.dist-info/RECORD
