Metadata-Version: 2.3
Name: dorkas_core
Version: 0.1.3
Classifier: Programming Language :: Python :: 3
Classifier: License :: OSI Approved :: MIT License
Classifier: Operating System :: OS Independent
Summary: dorkas
Author-email: Cody <cody@dkdc.dev>
Requires-Python: >=3.11
Project-URL: Homepage, https://github.com/lostmygithubaccount/dorkas
Project-URL: Bug Tracker, https://github.com/lostmygithubaccount/dorkas/issues
